ziwia/__init__.py
ziwia/api.py
ziwia/version.py
ziwia-0.2.0.dist-info/DESCRIPTION.rst
ziwia-0.2.0.dist-info/METADATA
ziwia-0.2.0.dist-info/RECORD
ziwia-0.2.0.dist-info/WHEEL
ziwia-0.2.0.dist-info/metadata.json
ziwia-0.2.0.dist-info/top_level.txt
ziwia-0.2.0.dist-info/zip-safe
