Metadata-Version: 2.0
Name: ziwia
Version: 0.2.0
Summary: API client for Kraken cryptocurrency trading site.
Home-page: http://github.com/malja/ziwia
Author: Jan Malčák
Author-email: jan@malcakov.cz
License: MIT
Keywords: kraken bitcoin cryptocurrency exchange client api rest
Platform: UNKNOWN
Classifier: Development Status :: 4 - Beta
Classifier: Intended Audience :: Developers
Classifier: Topic :: Internet
Classifier: License :: OSI Approved :: MIT License
Classifier: Programming Language :: Python :: 3
Classifier: Natural Language :: English
Classifier: Operating System :: Microsoft :: Windows
Classifier: Operating System :: POSIX :: Linux
Requires: requests
